{
    "configurations": [
        {
            "name": "Linux",
            "includePath": [
                "${workspaceFolder}/**",
                "/external/opencv/install/arm/include/opencv4",
                "/external/opencv/install/arm/include/opencv4/opencv2",
                "${workspaceFolder}/include",
                "${workspaceFolder}/include/ncnn"
            ],
            "defines": [],
            "compilerPath": "/usr/bin/clang",
            "cStandard": "c11",
            "cppStandard": "c++14",
            "intelliSenseMode": "linux-clang-x64"
        }
    ],
    "version": 4
}